LICENSE
MANIFEST.in
README.md
README.rst
setup.py
src/py_code_helpers/__init__.py
src/py_code_helpers.egg-info/PKG-INFO
src/py_code_helpers.egg-info/SOURCES.txt
src/py_code_helpers.egg-info/dependency_links.txt
src/py_code_helpers.egg-info/not-zip-safe
src/py_code_helpers.egg-info/top_level.txt
src/py_code_helpers/config_helper/__init__.py
src/py_code_helpers/config_helper/helper.py
src/py_code_helpers/log_helper/__init__.py
src/py_code_helpers/log_helper/helper.py