Metadata-Version: 1.1
Name: py-code-helpers
Version: 1.0.12
Summary: Code helpers
Home-page: https://tempfil.es
Author: Marco Antonio Albero Albero
Author-email: marco@mybi.es
License: Apache License, Version 2.0
Keywords: ready to go code helpers,development helpers
Platform: UNKNOWN
Classifier: Development Status :: 5 - Production/Stable
Classifier: Intended Audience :: Developers
Classifier: Intended Audience :: System Administrators
Classifier: Natural Language :: English
Classifier: Operating System :: OS Independent
Classifier: Programming Language :: Python
Classifier: Programming Language :: Python :: Implementation :: PyPy
